Metadata-Version: 2.1
Name: ai-university-AIU
Version: 1.0.0
Summary: Module for recognizing the MNIST-dataset
Home-page: UNKNOWN
Author: AI University
Author-email: nejronki@gmail.compile
License: UNKNOWN
Platform: UNKNOWN
Classifier: Programming Language :: Python :: 3
Classifier: License :: OSI Approved :: MIT License
Classifier: Operating System :: OS Independent
Requires-Python: >=3.6
